OylanAPI/__init__.py
OylanAPI/client.py
OylanAPI/constants.py
OylanAPI/exceptions.py
OylanAPI-0.1.0.dist-info/METADATA
OylanAPI-0.1.0.dist-info/WHEEL
OylanAPI-0.1.0.dist-info/top_level.txt
OylanAPI-0.1.0.dist-info/RECORD
