Metadata-Version: 2.2
Name: OylanAPI
Version: 0.1.0
Summary: A Python client for the Oylan Assistant API
Home-page: https://github.com/Dari4ok/OylanAPI
Author: Your Name
Author-email: dari4ok.vsl@gmail.com
Classifier: Programming Language :: Python :: 3
Classifier: License :: OSI Approved :: MIT License
Classifier: Operating System :: OS Independent
Requires-Python: >=3.7
Requires-Dist: requests>=2.20.0
Dynamic: author
Dynamic: author-email
Dynamic: classifier
Dynamic: description
Dynamic: description-content-type
Dynamic: home-page
Dynamic: requires-dist
Dynamic: requires-python
Dynamic: summary
